dhe-0.3.0.dist-info/METADATA
dhe-0.3.0.dist-info/WHEEL
dhe-0.3.0.dist-info/entry_points.txt
dhe/model.py
dhe/translations.py
dhe/c_dhe/numerics.h
dhe/c_dhe/numerics.c
dhe/c_dhe/c_dhe_core.c
dhe/c_dhe/c_dhe.h
dhe/c_dhe/c_dhe_core_module.c
dhe/c_dhe/c_dhe_module.c
dhe/c_dhe/c_dhe_core.h
dhe/c_dhe/c_dhe.c
dhe/__init__.py
dhe/gui.py
dhe/serialize.py
dhe/backends/__init__.py
dhe/backends/rs.py
dhe/backends/decorators.py
dhe/backends/c_core.py
dhe/backends/py.py
dhe/backends/c.py
dhe/classify.py
dhe/core.py
dhe/numerics.py
dhe/enum_map.py
dhe/cli.py
dhe/deserialize.py
dhe/io_formats.py
dhe/dhe.cpython-39-x86_64-linux-gnu.so
dhe-0.3.0.dist-info/RECORD
