Metadata-Version: 2.1
Name: dhe
Version: 0.3.0
Requires-Dist: numpy
Requires-Dist: scipy
Requires-Dist: wxPython[gui]
Summary: Downhole heat exchanger simulation
Author: Gerhard Bräunlich <g.braeunlich@disroot.org>
Author-Email: Gerhard Bräunlich <g.braeunlich@disroot.org>
